lime/__init__.py
lime/main.py
lime/commands/__init__.py
lime/commands/agg.py
lime/commands/check.py
lime/commands/eval.py
lime/commands/grade.py
lime/commands/initialize.py
lime/common/__init__.py
lime/common/controllers/__init__.py
lime/common/controllers/config_parse.py
lime/common/controllers/parse.py
lime/common/grading/__init__.py
lime/common/grading/base.py
lime/common/grading/fuzzy.py
lime/common/inference/__init__.py
lime/common/inference/api_openai.py
lime/common/inference/base.py
lime/common/inference/cpl_client.py
lime/common/inference/cpl_server.py
lime/common/inference/interface.py
lime/common/inference/local_llama_cpp.py
lime/common/models/__init__.py
lime/common/models/config.py
lime/common/models/errs.py
lime/common/models/internal.py
lime/common/models/state.py
lime/common/models/utils.py
lime/common/views/__init__.py
lime/common/views/agg/__init__.py
lime/common/views/agg/collect.py
lime/common/views/agg/query.py
lime/common/views/agg/utils.py
lime/common/views/msg/__init__.py
lime/common/views/msg/eval.py
lime/data/md-schema.yaml
lime/data/sheet-example.md
lime/data/config_model/__init__.py
lime/data/config_model/template.yaml
lime/data/datasets/simple/input-common-sense-1.md
lime/data/datasets/simple/input-common-sense-2.md
lime/data/datasets/simple/readme.md
lime_green-0.1.0.dist-info/METADATA
lime_green-0.1.0.dist-info/WHEEL
lime_green-0.1.0.dist-info/entry_points.txt
lime_green-0.1.0.dist-info/top_level.txt
lime_green-0.1.0.dist-info/RECORD
