Metadata-Version: 2.1
Name: lime-green
Version: 0.1.0
Summary: A cli based micro-framework for LLM evals
Author: Will Sutton
Author-email: Will Sutton <wsutton17@gmail.com>
Project-URL: Homepage, https://github.com/sutt/lime
Project-URL: Issues, https://github.com/sutt/lime/issues
Classifier: Programming Language :: Python :: 3
Classifier: License :: OSI Approved :: MIT License
Classifier: Operating System :: OS Independent
Requires-Python: >=3.8
Requires-Dist: PyYAML
Requires-Dist: python-dotenv
Requires-Dist: pydantic
Requires-Dist: pandas
Requires-Dist: tabulate
Requires-Dist: openai
Requires-Dist: tiktoken
Requires-Dist: flask
Provides-Extra: dev
Requires-Dist: pytest ; extra == 'dev'
Requires-Dist: jupyter ; extra == 'dev'
Requires-Dist: llama-cpp-python ; extra == 'dev'
Provides-Extra: llama_cpp
Requires-Dist: llama-cpp-python ; extra == 'llama_cpp'
